license.txt
ichika_utils/__init__.py
ichika_utils/basic.py
ichika_utils/lin_regression.py
ichika_utils/main.py
ichika_utils-0.1.6.dist-info/WHEEL
ichika_utils-0.1.6.dist-info/METADATA
ichika_utils-0.1.6.dist-info/RECORD
